snapper_mcp/__init__.py
snapper_mcp/server.py
snapper_mcp-0.1.1.dist-info/METADATA
snapper_mcp-0.1.1.dist-info/WHEEL
snapper_mcp-0.1.1.dist-info/entry_points.txt
snapper_mcp-0.1.1.dist-info/RECORD
