Metadata-Version: 2.4
Name: snapper-mcp
Version: 0.1.1
Summary: MCP server for managing BTRFS snapshots via Snapper
Project-URL: Homepage, https://github.com/danielrosehill/BTRFS-Snapper-MCP
Project-URL: Repository, https://github.com/danielrosehill/BTRFS-Snapper-MCP
Project-URL: Issues, https://github.com/danielrosehill/BTRFS-Snapper-MCP/issues
Author-email: Daniel Rosehill <public@danielrosehill.com>
License-Expression: MIT
Keywords: btrfs,filesystem,mcp,snapper,snapshots
Classifier: Development Status :: 4 - Beta
Classifier: Environment :: Console
Classifier: Intended Audience :: System Administrators
Classifier: License :: OSI Approved :: MIT License
Classifier: Operating System :: POSIX :: Linux
Classifier: Programming Language :: Python :: 3
Classifier: Programming Language :: Python :: 3.10
Classifier: Programming Language :: Python :: 3.11
Classifier: Programming Language :: Python :: 3.12
Classifier: Topic :: System :: Filesystems
Classifier: Topic :: System :: Systems Administration
Requires-Python: >=3.10
Requires-Dist: mcp>=1.0.0
Requires-Dist: pydantic>=2.0.0
Provides-Extra: dev
Requires-Dist: pytest-asyncio>=0.21.0; extra == 'dev'
Requires-Dist: pytest>=7.0.0; extra == 'dev'
